Metadata-Version: 2.1
Name: emailfly
Version: 1.0.1
Summary: Simple library to write python emails
Home-page: https://github.com/samrath-est/mailer.git
Author: EncoreSky Technologies
Author-email: samrathpatidar@encoresky.com
License: MIT
Platform: UNKNOWN
